{
  "template_name": "passport.jpg",
  "fields": {
    "фамилия": {
      "x": 200,
      "y": 150,
      "font_size": 24,
      "color": "#000000"
    },
    "имя": {
      "x": 200,
      "y": 200,
      "font_size": 24,
      "color": "#000000"
    },
    "отчество": {
      "x": 200,
      "y": 250,
      "font_size": 24,
      "color": "#000000"
    },
    "дата_рождения": {
      "x": 450,
      "y": 300,
      "font_size": 20,
      "color": "#000000"
    },
    "место_рождения": {
      "x": 200,
      "y": 350,
      "font_size": 18,
      "color": "#000000"
    },
    "серия_номер": {
      "x": 400,
      "y": 400,
      "font_size": 20,
      "color": "#000000"
    },
    "дата_выдачи": {
      "x": 200,
      "y": 450,
      "font_size": 18,
      "color": "#000000"
    },
    "кем_выдан": {
      "x": 200,
      "y": 500,
      "font_size": 16,
      "color": "#000000"
    }
  },
  "created_at": "2024-01-01"
}